fastgpu/__init__.py
fastgpu/_nbdev.py
fastgpu/cli.py
fastgpu/core.py
fastgpu-1.0.1.dist-info/LICENSE
fastgpu-1.0.1.dist-info/METADATA
fastgpu-1.0.1.dist-info/WHEEL
fastgpu-1.0.1.dist-info/entry_points.txt
fastgpu-1.0.1.dist-info/top_level.txt
fastgpu-1.0.1.dist-info/RECORD
