Metadata-Version: 2.1
Name: fastgpu
Version: 1.0.1
Summary: A queue service for quickly developing scripts that use all your GPUs efficiently
Home-page: https://github.com/fastai/fastgpu
Author: Jeremy Howard
Author-email: info@fast.ai
License: Apache Software License 2.0
Keywords: GPU fast.ai queue watchdog
Platform: UNKNOWN
Classifier: Development Status :: 5 - Production/Stable
Classifier: Intended Audience :: Developers
Classifier: License :: OSI Approved :: Apache Software License
Classifier: Natural Language :: English
Classifier: Programming Language :: Python :: 3.6
Classifier: Programming Language :: Python :: 3.7
Classifier: Programming Language :: Python :: 3.8
Requires-Python: >=3.6
Requires-Dist: fastcore (>=1.0.0)
